Andreani_QA_Api/Api.py
Andreani_QA_Api/__init__.py
Andreani_QA_Api-0.0.14.dist-info/METADATA
Andreani_QA_Api-0.0.14.dist-info/WHEEL
Andreani_QA_Api-0.0.14.dist-info/top_level.txt
Andreani_QA_Api-0.0.14.dist-info/RECORD
