Metadata-Version: 2.1
Name: Andreani-QA-Api
Version: 0.0.14
Summary: Funciones de API para ejecución de casos automatizados
Home-page: UNKNOWN
Author: AndreaniTesting
Author-email: user_appglatest@andreani.com
License: MIT
Platform: UNKNOWN
Requires-Dist: jsondiff
Requires-Dist: jsonschema
